setup.py
ngkel_distributions/Binomialdistribution.py
ngkel_distributions/Gaussiandistribution.py
ngkel_distributions/Generaldistribution.py
ngkel_distributions/__init__.py
ngkel_distributions.egg-info/PKG-INFO
ngkel_distributions.egg-info/SOURCES.txt
ngkel_distributions.egg-info/dependency_links.txt
ngkel_distributions.egg-info/not-zip-safe
ngkel_distributions.egg-info/top_level.txt