Metadata-Version: 1.0
Name: ngkel-distributions
Version: 0.1
Summary: Gaussian and Binomial distributions
Home-page: UNKNOWN
Author: UNKNOWN
Author-email: ngkel@connect.hku.hk
License: UNKNOWN
Platform: UNKNOWN
